mmead/__init__.py
mmead/connection.py
mmead/download_info.py
mmead/retrieve.py
mmead/util.py
mmead/data/__init__.py
mmead/data/embeddings.py
mmead/data/links.py
mmead/data/mappings.py
mmead-0.1.0.dist-info/LICENSE
mmead-0.1.0.dist-info/METADATA
mmead-0.1.0.dist-info/WHEEL
mmead-0.1.0.dist-info/top_level.txt
mmead-0.1.0.dist-info/RECORD
