Metadata-Version: 2.1
Name: mmead
Version: 0.1.0
Summary: MS MARCO entity annotations and disambiguations
Home-page: https://github.com/informagi/mmead
Author: Chris Kamphuis
Author-email: chris@cs.ru.nl
Requires-Python: >=3.6
License-File: LICENSE
Requires-Dist: tqdm
Requires-Dist: numpy
Requires-Dist: duckdb
